src/GCT.py
src/__init__.py
GCT-1.0.dist-info/LICENSE
GCT-1.0.dist-info/METADATA
GCT-1.0.dist-info/WHEEL
GCT-1.0.dist-info/top_level.txt
GCT-1.0.dist-info/RECORD
