Metadata-Version: 2.1
Name: GCT
Version: 1.0
Summary: Generate a GCT file
Home-page: 
Author: Julien Moehlin
License: LICENSE.txt
Platform: UNKNOWN
Requires-Python: >=2.7
License-File: LICENSE
Requires-Dist: numpy
